flest/__init__.py
flest/_self.py
flest/_utils.py
flest/config.py
flest/decorators.py
Flest-0.1.26.dist-info/METADATA
Flest-0.1.26.dist-info/WHEEL
Flest-0.1.26.dist-info/entry_points.txt
Flest-0.1.26.dist-info/top_level.txt
Flest-0.1.26.dist-info/RECORD
