Metadata-Version: 2.1
Name: Flest
Version: 0.1.26
Summary: Flest - small contribution to Flask world.
Home-page: http://tbd
Author: Jihwan Song
Author-email: jihwan2@gmail.com
License: MIT
Platform: UNKNOWN
Classifier: License :: OSI Approved :: MIT License
Classifier: Programming Language :: Python :: 3
Classifier: Programming Language :: Python :: 3.7
Requires-Python: >=3.6
Requires-Dist: Flask
Requires-Dist: decorator
